ridge_utils/DataSequence.py
ridge_utils/SemanticModel.py
ridge_utils/__init__.py
ridge_utils/dsutils.py
ridge_utils/interpdata.py
ridge_utils/npp.py
ridge_utils/ridge.py
ridge_utils/stimulus_utils.py
ridge_utils/textgrid.py
ridge_utils/tokenization_helpers.py
ridge_utils/util.py
ridge_utils/utils.py
ridge_utils-0.2.dist-info/METADATA
ridge_utils-0.2.dist-info/WHEEL
ridge_utils-0.2.dist-info/top_level.txt
ridge_utils-0.2.dist-info/RECORD
